senaite.lims-1.3.1-py2.7-nspkg.pth
senaite/.DS_Store
senaite/lims/.DS_Store
senaite/lims/__init__.py
senaite/lims/config.py
senaite/lims/configure.zcml
senaite/lims/interfaces.py
senaite/lims/setuphandlers.py
senaite/lims/browser/.DS_Store
senaite/lims/browser/__init__.py
senaite/lims/browser/configure.zcml
senaite/lims/browser/backbone/__init__.py
senaite/lims/browser/backbone/configure.zcml
senaite/lims/browser/backbone/static/js/backbone-min.js
senaite/lims/browser/backbone/static/js/underscore-min.js
senaite/lims/browser/bootstrap/Readme.md
senaite/lims/browser/bootstrap/__init__.py
senaite/lims/browser/bootstrap/adapters.py
senaite/lims/browser/bootstrap/configure.zcml
senaite/lims/browser/bootstrap/interfaces.py
senaite/lims/browser/bootstrap/portlets.py
senaite/lims/browser/bootstrap/viewlets.py
senaite/lims/browser/bootstrap/views.py
senaite/lims/browser/bootstrap/skins/bootstrap_templates/global_statusmessage.pt
senaite/lims/browser/bootstrap/skins/bootstrap_templates/login_form.cpt
senaite/lims/browser/bootstrap/skins/bootstrap_templates/login_form.cpt.metadata
senaite/lims/browser/bootstrap/static/coffee/bootstrap-integration.coffee
senaite/lims/browser/bootstrap/static/css/bootstrap-integration.css
senaite/lims/browser/bootstrap/static/js/bootstrap-integration.js
senaite/lims/browser/bootstrap/templates/bika.lims.browser.templates.instrument_qc_failures_viewlet.pt
senaite/lims/browser/bootstrap/templates/bika.lims.browser.viewlets.templates.attachments.pt
senaite/lims/browser/bootstrap/templates/bika.lims.browser.viewlets.templates.worksheet_attachments.pt
senaite/lims/browser/bootstrap/templates/plone.app.contentmenu.contentmenu.pt
senaite/lims/browser/bootstrap/templates/plone.app.controlpanel.overview.pt
senaite/lims/browser/bootstrap/templates/plone.app.i18n.locales.browser.languageselector.pt
senaite/lims/browser/bootstrap/templates/plone.app.layout.viewlets.colophon.pt
senaite.lims-1.3.1.dist-info/LICENSE
senaite.lims-1.3.1.dist-info/METADATA
senaite.lims-1.3.1.dist-info/WHEEL
senaite.lims-1.3.1.dist-info/entry_points.txt
senaite.lims-1.3.1.dist-info/namespace_packages.txt
senaite.lims-1.3.1.dist-info/top_level.txt
senaite.lims-1.3.1.dist-info/RECORD
