Metadata-Version: 2.1
Name: senaite.lims
Version: 1.3.1
Summary: SENAITE LIMS - Meta Package for Core and UI/UX Components
Home-page: https://github.com/senaite/senaite.lims
Author: SENAITE Foundation
Author-email: hello@senaite.com
License: GPLv2
Platform: UNKNOWN
Classifier: Framework :: Plone
Classifier: Framework :: Zope2
Classifier: Programming Language :: Python
Classifier: Development Status :: 5 - Production/Stable
Classifier: License :: OSI Approved :: GNU General Public License v2 (GPLv2)
Requires-Dist: senaite.api
Requires-Dist: senaite.core.listing (>=1.2.0)
Requires-Dist: senaite.core (>=1.3.1)
Requires-Dist: senaite.impress (>=1.2.1)
Requires-Dist: senaite.jsonapi
Requires-Dist: setuptools
Provides-Extra: test
Requires-Dist: Products.PloneTestCase ; extra == 'test'
Requires-Dist: Products.SecureMailHost ; extra == 'test'
Requires-Dist: plone.app.testing ; extra == 'test'
Requires-Dist: unittest2 ; extra == 'test'
